arey/__init__.py
arey/ai.py
arey/chat.py
arey/config.py
arey/error.py
arey/main.py
arey/play.py
arey/prompt.py
arey/task.py
arey/data/config.yml
arey/data/play.md
arey/data/prompts/alpaca.yml
arey/data/prompts/chatml.yml
arey/data/prompts/codegeex4.yml
arey/data/prompts/gemma2.yml
arey/data/prompts/llama3.yml
arey/data/prompts/magicoder.yml
arey/data/prompts/opencodeinterpreter.yml
arey/data/prompts/openorca.yml
arey/data/prompts/phi3.yml
arey/data/prompts/synthia.yml
arey/platform/__init__.py
arey/platform/_llama.py
arey/platform/_ollama.py
arey/platform/_openai.py
arey/platform/assets.py
arey/platform/console.py
arey/platform/llm.py
arey-0.0.6.dist-info/LICENSE
arey-0.0.6.dist-info/METADATA
arey-0.0.6.dist-info/WHEEL
arey-0.0.6.dist-info/entry_points.txt
arey-0.0.6.dist-info/top_level.txt
arey-0.0.6.dist-info/RECORD
