Metadata-Version: 2.1
Name: arey
Version: 0.0.6
Summary: Simple large language model playground.
Author-email: codito <codito@codito.in>
Project-URL: Homepage, https://github.com/codito/arey
Project-URL: Documentation, https://apps.codito.in/arey
Project-URL: Source, https://github.com/codito/arey
Project-URL: Changelog, https://github.com/codito/arey/blob/master/CHANGELOG.md
Classifier: Development Status :: 2 - Pre-Alpha
Classifier: Environment :: Console
Classifier: Programming Language :: Python
Classifier: Programming Language :: Python :: 3
Classifier: Programming Language :: Python :: 3 :: Only
Classifier: Programming Language :: Python :: 3.10
Classifier: Programming Language :: Python :: 3.11
Classifier: Programming Language :: Python :: 3.12
Classifier: Intended Audience :: Developers
Classifier: Intended Audience :: Information Technology
Classifier: License :: OSI Approved :: MIT License
Classifier: Operating System :: POSIX :: Linux
Classifier: Operating System :: Microsoft :: Windows
Classifier: Operating System :: MacOS
Classifier: Topic :: Communications :: Chat
Classifier: Topic :: Scientific/Engineering :: Artificial Intelligence
Classifier: Topic :: Terminals
Classifier: Topic :: Utilities
Classifier: Topic :: Text Processing :: Markup :: Markdown
Requires-Python: >=3.10
License-File: LICENSE
Requires-Dist: click >=8.1.7
Requires-Dist: llama-cpp-python >=0.2.85
Requires-Dist: markdown >=3.5.2
Requires-Dist: ollama >=0.1.6
Requires-Dist: openai >=1.12.0
Requires-Dist: python-frontmatter >=1.1.0
Requires-Dist: pyyaml >=6.0.1
Requires-Dist: rich >=13.7.0
Requires-Dist: tiktoken >=0.6.0
Requires-Dist: watchfiles >=0.21.0
Requires-Dist: wurlitzer >=3.0.3
Provides-Extra: samples
Requires-Dist: beautifulsoup4 ; extra == 'samples'
Requires-Dist: lxml ; extra == 'samples'
Provides-Extra: test
Requires-Dist: mkdocs ; extra == 'test'
Requires-Dist: mkdocs-material ; extra == 'test'
Requires-Dist: pre-commit ; extra == 'test'
Requires-Dist: pytest ; extra == 'test'
Requires-Dist: pytest-mock ; extra == 'test'
Requires-Dist: pytest-cov ; extra == 'test'
Requires-Dist: ruff ; extra == 'test'
